polyagent-1.2.1.dist-info/licenses/LICENSE
polycli/__init__.py
polycli/adapters.py
polycli/cli.py
polycli/event.py
polycli/message.py
polycli/polyagent.py
polycli/clients/__init__.py
polycli/clients/api.py
polycli/clients/base.py
polycli/clients/claude.py
polycli/clients/codex.py
polycli/clients/miniswe.py
polycli/clients/qwen.py
polycli/integrations/__init__.py
polycli/integrations/fastapi.py
polycli/orchestration/__init__.py
polycli/orchestration/builtin_patterns.py
polycli/orchestration/orchestration.py
polycli/orchestration/session_registry.py
polycli/sandbox/__init__.py
polycli/sandbox/runner.py
polycli/scripts/__init__.py
polycli/scripts/claude_hooks.py
polycli/scripts/hook_bridge.py
polycli/ui/control_panel.html
polycli/ui/monitor.html
polycli/ui/monitor.js
polycli/utils/__init__.py
polycli/utils/chat.py
polycli/utils/llm_client.py
polycli/utils/model_config.py
polycli/utils/serializers.py
polycli/utils/watcher.py
polyagent-1.2.1.dist-info/METADATA
polyagent-1.2.1.dist-info/WHEEL
polyagent-1.2.1.dist-info/entry_points.txt
polyagent-1.2.1.dist-info/top_level.txt
polyagent-1.2.1.dist-info/RECORD
