Metadata-Version: 2.4
Name: polyagent
Version: 1.2.1
Summary: A unified interface for managing stateful conversations with various CLI-based AI agents
Requires-Python: >=3.8
License-File: LICENSE
Requires-Dist: instructor
Requires-Dist: openai
Requires-Dist: pydantic
Requires-Dist: python-dotenv
Requires-Dist: click>=8.0
Requires-Dist: httpx[socks]
Provides-Extra: dev
Requires-Dist: pytest; extra == "dev"
Requires-Dist: black; extra == "dev"
Requires-Dist: ruff; extra == "dev"
Provides-Extra: fastapi
Requires-Dist: fastapi>=0.100.0; extra == "fastapi"
Requires-Dist: uvicorn[standard]>=0.20.0; extra == "fastapi"
Dynamic: license-file
